{
  "season": 2026,
  "pitch_types": {
    "CH": {
      "count": 2886,
      "velo": 85.8,
      "spin": 1739,
      "zone_pct": 32.2,
      "whiff_pct": 29.6,
      "extension": 6.4
    },
    "CU": {
      "count": 1697,
      "velo": 79.7,
      "spin": 2541,
      "zone_pct": 35.6,
      "whiff_pct": 32.2,
      "extension": 6.36
    },
    "FC": {
      "count": 2077,
      "velo": 89.1,
      "spin": 2374,
      "zone_pct": 46.9,
      "whiff_pct": 22.8,
      "extension": 6.4
    },
    "FF": {
      "count": 7619,
      "velo": 94.5,
      "spin": 2309,
      "zone_pct": 47.9,
      "whiff_pct": 22.3,
      "extension": 6.5
    },
    "FS": {
      "count": 784,
      "velo": 86.4,
      "spin": 1375,
      "zone_pct": 32.4,
      "whiff_pct": 31.9,
      "extension": 6.6
    },
    "SI": {
      "count": 4090,
      "velo": 93.9,
      "spin": 2170,
      "zone_pct": 51.8,
      "whiff_pct": 13.0,
      "extension": 6.4
    },
    "SL": {
      "count": 3137,
      "velo": 86.0,
      "spin": 2413,
      "zone_pct": 40.3,
      "whiff_pct": 33.3,
      "extension": 6.4
    },
    "ST": {
      "count": 2081,
      "velo": 82.5,
      "spin": 2577,
      "zone_pct": 38.1,
      "whiff_pct": 30.4,
      "extension": 6.31
    }
  },
  "generated_at": "2026-04-13 11:23:04 UTC"
}