{
  "season": 2026,
  "league": "MLB",
  "starters": [],
  "relievers": [
    {
      "player_id": 605280,
      "name": "Clay Holmes",
      "team": "NYM",
      "ip": 22.0,
      "gs": 3,
      "is_sp": false,
      "avg_pitches_to_2k": 2.804,
      "qualifying_pas": 46,
      "total_pas": 89,
      "reach_pct": 51.7,
      "pctile": 100.0
    },
    {
      "player_id": 608331,
      "name": "Max Fried",
      "team": "NYY",
      "ip": 20.9,
      "gs": 2,
      "is_sp": false,
      "avg_pitches_to_2k": 2.829,
      "qualifying_pas": 35,
      "total_pas": 76,
      "reach_pct": 46.1,
      "pctile": 66.7
    },
    {
      "player_id": 686799,
      "name": "Jack Kochanowicz",
      "team": "LAA",
      "ip": 20.0,
      "gs": 3,
      "is_sp": false,
      "avg_pitches_to_2k": 3.25,
      "qualifying_pas": 32,
      "total_pas": 79,
      "reach_pct": 40.5,
      "pctile": 33.3
    }
  ],
  "meta": {
    "min_ip": 20,
    "gs_threshold": 10,
    "total_pitches_analyzed": 50000,
    "generated_at": "2026-04-29 11:31:49 UTC"
  }
}